{"data":"{\"fetchStatus\":\"ok\",\"data\":{\"data\":{\"__typename\":\"Tweet\",\"lang\":\"en\",\"favorite_count\":9,\"possibly_sensitive\":false,\"created_at\":\"2025-01-28T15:48:10.000Z\",\"display_text_range\":[0,225],\"entities\":{\"hashtags\":[],\"urls\":[{\"display_url\":\"react-flip-children.alfon.dev/heroui\",\"expanded_url\":\"https://react-flip-children.alfon.dev/heroui\",\"indices\":[201,224],\"url\":\"https://t.co/CMLBbRf3OY\"}],\"user_mentions\":[{\"id_str\":\"1399866136787918850\",\"indices\":[70,78],\"name\":\"HeroUI\",\"screen_name\":\"hero_ui\"}],\"symbols\":[],\"media\":[{\"display_url\":\"pic.x.com/yIaWbBJKDX\",\"expanded_url\":\"https://x.com/alfonsusac/status/1884267231816868327/photo/1\",\"indices\":[225,248],\"url\":\"https://t.co/yIaWbBJKDX\"}]},\"id_str\":\"1884267231816868327\",\"text\":\"Just like shad's, Its also easy to integrate React Flip Children with @hero_ui.\\n\\nAlthough I found a bug with the Image making new request change for every change of array\\n\\nCheck out the \\\"guide\\\" here 👀\\nhttps://t.co/CMLBbRf3OY https://t.co/yIaWbBJKDX\",\"user\":{\"id_str\":\"300240474\",\"name\":\"Alfon\",\"screen_name\":\"alfonsusac\",\"is_blue_verified\":false,\"profile_image_shape\":\"Circle\",\"verified\":false,\"profile_image_url_https\":\"https://pbs.twimg.com/profile_images/1995396591155625984/kuIyQvsn_normal.jpg\"},\"edit_control\":{\"edit_tweet_ids\":[\"1884267231816868327\"],\"editable_until_msecs\":\"1738082890000\",\"is_edit_eligible\":true,\"edits_remaining\":\"5\"},\"mediaDetails\":[{\"display_url\":\"pic.x.com/yIaWbBJKDX\",\"expanded_url\":\"https://x.com/alfonsusac/status/1884267231816868327/photo/1\",\"ext_media_availability\":{\"status\":\"Available\"},\"indices\":[225,248],\"media_url_https\":\"https://pbs.twimg.com/media/GiY7fQ6aYAETx_j.jpg\",\"original_info\":{\"height\":1772,\"width\":2576,\"focus_rects\":[{\"x\":0,\"y\":0,\"w\":2576,\"h\":1443},{\"x\":0,\"y\":0,\"w\":1772,\"h\":1772},{\"x\":60,\"y\":0,\"w\":1554,\"h\":1772},{\"x\":394,\"y\":0,\"w\":886,\"h\":1772},{\"x\":0,\"y\":0,\"w\":2576,\"h\":1772}]},\"sizes\":{\"large\":{\"h\":1409,\"resize\":\"fit\",\"w\":2048},\"medium\":{\"h\":825,\"resize\":\"fit\",\"w\":1200},\"small\":{\"h\":468,\"resize\":\"fit\",\"w\":680},\"thumb\":{\"h\":150,\"resize\":\"crop\",\"w\":150}},\"type\":\"photo\",\"url\":\"https://t.co/yIaWbBJKDX\"}],\"photos\":[{\"backgroundColor\":{\"red\":204,\"green\":214,\"blue\":221},\"cropCandidates\":[{\"x\":0,\"y\":0,\"w\":2576,\"h\":1443},{\"x\":0,\"y\":0,\"w\":1772,\"h\":1772},{\"x\":60,\"y\":0,\"w\":1554,\"h\":1772},{\"x\":394,\"y\":0,\"w\":886,\"h\":1772},{\"x\":0,\"y\":0,\"w\":2576,\"h\":1772}],\"expandedUrl\":\"https://x.com/alfonsusac/status/1884267231816868327/photo/1\",\"url\":\"https://pbs.twimg.com/media/GiY7fQ6aYAETx_j.jpg\",\"width\":2576,\"height\":1772}],\"conversation_count\":0,\"news_action_type\":\"conversation\",\"isEdited\":false,\"isStaleEdit\":false}}}","createdAt":1775214751089,"staleAt":1775215051089,"expiryAt":1775215351089}